karrotcapital/__init__.py
karrotcapital/spiderswap/__init__.py
karrotcapital/spiderswap/quote.py
karrotcapital/spiderswap/swap.py
karrotcapital/spiderswap/tests/__init__.py
karrotcapital/spiderswap/tests/conftest.py
karrotcapital/spiderswap/tests/test_quote.py
karrotcapital/spiderswap/tests/test_swap.py
karrotcapital.spiderswap-1.0.2.dist-info/LICENSE
karrotcapital.spiderswap-1.0.2.dist-info/METADATA
karrotcapital.spiderswap-1.0.2.dist-info/WHEEL
karrotcapital.spiderswap-1.0.2.dist-info/top_level.txt
karrotcapital.spiderswap-1.0.2.dist-info/RECORD
