Metadata-Version: 2.1
Name: karrotcapital.spiderswap
Version: 1.0.2
Summary: A package for interacting with the SpiderSwap API
Home-page: https://docs.karrot.capital
Author: Dutch - Karrot Capital
Author-email: dutch@karrot.capital
Classifier: Programming Language :: Python :: 3
Classifier: License :: OSI Approved :: MIT License
Classifier: Operating System :: OS Independent
Requires-Python: >=3.6
License-File: LICENSE
Requires-Dist: aiohttp >=3.7.4
Requires-Dist: solana >=0.21.0
Requires-Dist: base58 >=2.1.0
Requires-Dist: solders
